{
  "token_alternative_map": {
    "cot": {
      "cot": [
        "Keep distance to the scooter ahead since it is directly in our lane"
      ],
      "meta_action": [
        ""
      ],
      "answer": [
        ""
      ]
    },
    "n_reasoning_tokens": 13,
    "mean_entropy": 0.46446535292153174,
    "positions": [
      {
        "step": 0,
        "col": 3086,
        "sampled": "Keep",
        "sampled_prob": 0.5580194592475891,
        "entropy": 1.261070966720581,
        "top_k": [
          {
            "text": "Keep",
            "prob": 0.5580194592475891
          },
          {
            "text": "N",
            "prob": 0.2805897891521454
          },
          {
            "text": "Y",
            "prob": 0.10649987310171127
          },
          {
            "text": "Acceler",
            "prob": 0.015342761762440205
          },
          {
            "text": "Slow",
            "prob": 0.00821238849312067
          }
        ]
      },
      {
        "step": 1,
        "col": 3087,
        "sampled": " distance",
        "sampled_prob": 0.9987725615501404,
        "entropy": 0.010173918679356575,
        "top_k": [
          {
            "text": " distance",
            "prob": 0.9987725615501404
          },
          {
            "text": " lane",
            "prob": 0.0010985895060002804
          },
          {
            "text": " at",
            "prob": 4.6783585275989026e-05
          },
          {
            "text": " left",
            "prob": 3.878495408571325e-05
          },
          {
            "text": " speed",
            "prob": 1.1112075299024582e-05
          }
        ]
      },
      {
        "step": 2,
        "col": 3088,
        "sampled": " to",
        "sampled_prob": 0.902679443359375,
        "entropy": 0.3603723645210266,
        "top_k": [
          {
            "text": " to",
            "prob": 0.902679443359375
          },
          {
            "text": " from",
            "prob": 0.08937736600637436
          },
          {
            "text": " since",
            "prob": 0.0036890446208417416
          },
          {
            "text": " because",
            "prob": 0.0028730309568345547
          },
          {
            "text": " due",
            "prob": 0.0003028151986654848
          }
        ]
      },
      {
        "step": 3,
        "col": 3089,
        "sampled": " the",
        "sampled_prob": 0.99856036901474,
        "entropy": 0.018120821565389633,
        "top_k": [
          {
            "text": " the",
            "prob": 0.99856036901474
          },
          {
            "text": " maintain",
            "prob": 0.0001582331897225231
          },
          {
            "text": " our",
            "prob": 0.0001054060339811258
          },
          {
            "text": " follow",
            "prob": 7.711669604759663e-05
          },
          {
            "text": " from",
            "prob": 6.393199146259576e-05
          }
        ]
      },
      {
        "step": 4,
        "col": 3090,
        "sampled": " scooter",
        "sampled_prob": 0.8895934224128723,
        "entropy": 0.9464749693870544,
        "top_k": [
          {
            "text": " scooter",
            "prob": 0.8895934224128723
          },
          {
            "text": " pedestrian",
            "prob": 0.04714672267436981
          },
          {
            "text": " cyclist",
            "prob": 0.013936544768512249
          },
          {
            "text": " lead",
            "prob": 0.003109663724899292
          },
          {
            "text": " rider",
            "prob": 0.0024986849166452885
          }
        ]
      },
      {
        "step": 5,
        "col": 3091,
        "sampled": " ahead",
        "sampled_prob": 0.6417021155357361,
        "entropy": 1.2644948959350586,
        "top_k": [
          {
            "text": " ahead",
            "prob": 0.6417021155357361
          },
          {
            "text": " rider",
            "prob": 0.26750123500823975
          },
          {
            "text": " in",
            "prob": 0.042324844747781754
          },
          {
            "text": " since",
            "prob": 0.00782930850982666
          },
          {
            "text": " because",
            "prob": 0.004323754925280809
          }
        ]
      },
      {
        "step": 6,
        "col": 3092,
        "sampled": " since",
        "sampled_prob": 0.9866630434989929,
        "entropy": 0.07804940640926361,
        "top_k": [
          {
            "text": " since",
            "prob": 0.9866630434989929
          },
          {
            "text": " because",
            "prob": 0.011667748913168907
          },
          {
            "text": " in",
            "prob": 0.0010852697305381298
          },
          {
            "text": " as",
            "prob": 0.00025777413975447416
          },
          {
            "text": " to",
            "prob": 0.00013797657447867095
          }
        ]
      },
      {
        "step": 7,
        "col": 3093,
        "sampled": " it",
        "sampled_prob": 0.9936370849609375,
        "entropy": 0.0453026220202446,
        "top_k": [
          {
            "text": " it",
            "prob": 0.9936370849609375
          },
          {
            "text": " they",
            "prob": 0.005550411529839039
          },
          {
            "text": " the",
            "prob": 0.00020859140204265714
          },
          {
            "text": " a",
            "prob": 9.256187331629917e-05
          },
          {
            "text": " an",
            "prob": 2.4146205760189332e-05
          }
        ]
      },
      {
        "step": 8,
        "col": 3094,
        "sampled": " is",
        "sampled_prob": 0.9835087656974792,
        "entropy": 0.10587657988071442,
        "top_k": [
          {
            "text": " is",
            "prob": 0.9835087656974792
          },
          {
            "text": " occupies",
            "prob": 0.014028999023139477
          },
          {
            "text": " moves",
            "prob": 0.00021301908418536186
          },
          {
            "text": " occupying",
            "prob": 0.00014190129877533764
          },
          {
            "text": " has",
            "prob": 8.606749906903133e-05
          }
        ]
      },
      {
        "step": 9,
        "col": 3095,
        "sampled": " directly",
        "sampled_prob": 0.5085107684135437,
        "entropy": 1.4293221235275269,
        "top_k": [
          {
            "text": " directly",
            "prob": 0.5085107684135437
          },
          {
            "text": " occupying",
            "prob": 0.21197882294654846
          },
          {
            "text": " in",
            "prob": 0.12857165932655334
          },
          {
            "text": " moving",
            "prob": 0.10658964514732361
          },
          {
            "text": " the",
            "prob": 0.015355694107711315
          }
        ]
      },
      {
        "step": 10,
        "col": 3096,
        "sampled": " in",
        "sampled_prob": 0.8987664580345154,
        "entropy": 0.3795918822288513,
        "top_k": [
          {
            "text": " in",
            "prob": 0.8987664580345154
          },
          {
            "text": " ahead",
            "prob": 0.08898993581533432
          },
          {
            "text": " blocking",
            "prob": 0.009984394535422325
          },
          {
            "text": " occupying",
            "prob": 0.0007699137204326689
          },
          {
            "text": " obstruct",
            "prob": 0.00019466466619633138
          }
        ]
      },
      {
        "step": 11,
        "col": 3097,
        "sampled": " our",
        "sampled_prob": 0.9916208982467651,
        "entropy": 0.04998132213950157,
        "top_k": [
          {
            "text": " our",
            "prob": 0.9916208982467651
          },
          {
            "text": " front",
            "prob": 0.00805941503494978
          },
          {
            "text": " the",
            "prob": 0.00029356416780501604
          },
          {
            "text": " your",
            "prob": 4.7450225792999845e-06
          },
          {
            "text": " my",
            "prob": 4.320391781220678e-06
          }
        ]
      },
      {
        "step": 12,
        "col": 3098,
        "sampled": " lane",
        "sampled_prob": 0.9849328398704529,
        "entropy": 0.08921771496534348,
        "top_k": [
          {
            "text": " lane",
            "prob": 0.9849328398704529
          },
          {
            "text": " path",
            "prob": 0.012398474849760532
          },
          {
            "text": " travel",
            "prob": 0.0021545318886637688
          },
          {
            "text": " same",
            "prob": 7.14557827450335e-05
          },
          {
            "text": " ego",
            "prob": 5.227816291153431e-05
          }
        ]
      }
    ]
  },
  "single_token_swap_sweep": [
    {
      "step": 0,
      "col": 3086,
      "sampled_token": "Keep",
      "sampled_prob": 0.5580194592475891,
      "entropy": 1.261070966720581,
      "alternatives": [
        {
          "token": "N",
          "token_prob": 0.2805897891521454,
          "d_curvature_mean": 1.7983282305067405e-05,
          "d_curvature_max": 5.229748785495758e-05,
          "endpoint_shift_m": 0.08750999718904495,
          "traj_ade_m": 0.023666076362133026,
          "forced_cot": {
            "cot": [
              "N distance to the scooter ahead since it is directly in our lane"
            ],
            "meta_action": [
              ""
            ],
            "answer": [
              ""
            ]
          }
        },
        {
          "token": "Y",
          "token_prob": 0.10649987310171127,
          "d_curvature_mean": 3.445848778937943e-05,
          "d_curvature_max": 8.163601160049438e-05,
          "endpoint_shift_m": 0.10169849544763565,
          "traj_ade_m": 0.0289754681289196,
          "forced_cot": {
            "cot": [
              "Y distance to the scooter ahead since it is directly in our lane"
            ],
            "meta_action": [
              ""
            ],
            "answer": [
              ""
            ]
          }
        },
        {
          "token": "Acceler",
          "token_prob": 0.015342761762440205,
          "d_curvature_mean": 3.2512281904928386e-05,
          "d_curvature_max": 7.143104448914528e-05,
          "endpoint_shift_m": 0.029433216899633408,
          "traj_ade_m": 0.01473339181393385,
          "forced_cot": {
            "cot": [
              "Acceler distance to the scooter ahead since it is directly in our lane"
            ],
            "meta_action": [
              ""
            ],
            "answer": [
              ""
            ]
          }
        },
        {
          "token": "Slow",
          "token_prob": 0.00821238849312067,
          "d_curvature_mean": 5.085978045826778e-05,
          "d_curvature_max": 0.00011734943836927414,
          "endpoint_shift_m": 0.07642102986574173,
          "traj_ade_m": 0.02551255188882351,
          "forced_cot": {
            "cot": [
              "Slow distance to the scooter ahead since it is directly in our lane"
            ],
            "meta_action": [
              ""
            ],
            "answer": [
              ""
            ]
          }
        }
      ]
    },
    {
      "step": 1,
      "col": 3087,
      "sampled_token": " distance",
      "sampled_prob": 0.9987725615501404,
      "entropy": 0.010173918679356575,
      "alternatives": [
        {
          "token": " lane",
          "token_prob": 0.0010985895060002804,
          "d_curvature_mean": 4.826321674045175e-05,
          "d_curvature_max": 9.183911606669426e-05,
          "endpoint_shift_m": 0.03129253908991814,
          "traj_ade_m": 0.0073984963819384575,
          "forced_cot": {
            "cot": [
              "Keep lane to the scooter ahead since it is directly in our lane"
            ],
            "meta_action": [
              ""
            ],
            "answer": [
              ""
            ]
          }
        },
        {
          "token": " at",
          "token_prob": 4.6783585275989026e-05,
          "d_curvature_mean": 3.398119588382542e-05,
          "d_curvature_max": 8.163601160049438e-05,
          "endpoint_shift_m": 0.11817031353712082,
          "traj_ade_m": 0.04338466376066208,
          "forced_cot": {
            "cot": [
              "Keep at to the scooter ahead since it is directly in our lane"
            ],
            "meta_action": [
              ""
            ],
            "answer": [
              ""
            ]
          }
        },
        {
          "token": " left",
          "token_prob": 3.878495408571325e-05,
          "d_curvature_mean": 0.00015645539679098874,
          "d_curvature_max": 0.00032908935099840164,
          "endpoint_shift_m": 0.4194490611553192,
          "traj_ade_m": 0.11946123838424683,
          "forced_cot": {
            "cot": [
              "Keep left to the scooter ahead since it is directly in our lane"
            ],
            "meta_action": [
              ""
            ],
            "answer": [
              ""
            ]
          }
        },
        {
          "token": " speed",
          "token_prob": 1.1112075299024582e-05,
          "d_curvature_mean": 0.00022485380759462714,
          "d_curvature_max": 0.0005102185532450676,
          "endpoint_shift_m": 0.6781615614891052,
          "traj_ade_m": 0.19881269335746765,
          "forced_cot": {
            "cot": [
              "Keep speed to the scooter ahead since it is directly in our lane"
            ],
            "meta_action": [
              ""
            ],
            "answer": [
              ""
            ]
          }
        }
      ]
    },
    {
      "step": 2,
      "col": 3088,
      "sampled_token": " to",
      "sampled_prob": 0.902679443359375,
      "entropy": 0.3603723645210266,
      "alternatives": [
        {
          "token": " from",
          "token_prob": 0.08937736600637436,
          "d_curvature_mean": 3.193143493263051e-05,
          "d_curvature_max": 7.892400026321411e-05,
          "endpoint_shift_m": 0.11019018292427063,
          "traj_ade_m": 0.03448295220732689,
          "forced_cot": {
            "cot": [
              "Keep distance from the scooter ahead since it is directly in our lane"
            ],
            "meta_action": [
              ""
            ],
            "answer": [
              ""
            ]
          }
        },
        {
          "token": " since",
          "token_prob": 0.0036890446208417416,
          "d_curvature_mean": 7.381191244348884e-05,
          "d_curvature_max": 0.00012245227117091417,
          "endpoint_shift_m": 0.032903023064136505,
          "traj_ade_m": 0.00851535890251398,
          "forced_cot": {
            "cot": [
              "Keep distance since the scooter ahead since it is directly in our lane"
            ],
            "meta_action": [
              ""
            ],
            "answer": [
              ""
            ]
          }
        },
        {
          "token": " because",
          "token_prob": 0.0028730309568345547,
          "d_curvature_mean": 0.00012508482905104756,
          "d_curvature_max": 0.0001836768351495266,
          "endpoint_shift_m": 0.17121288180351257,
          "traj_ade_m": 0.04650907218456268,
          "forced_cot": {
            "cot": [
              "Keep distance because the scooter ahead since it is directly in our lane"
            ],
            "meta_action": [
              ""
            ],
            "answer": [
              ""
            ]
          }
        },
        {
          "token": " due",
          "token_prob": 0.0003028151986654848,
          "d_curvature_mean": 6.0233935073483735e-05,
          "d_curvature_max": 0.00016326969489455223,
          "endpoint_shift_m": 0.20055121183395386,
          "traj_ade_m": 0.0809265598654747,
          "forced_cot": {
            "cot": [
              "Keep distance due the scooter ahead since it is directly in our lane"
            ],
            "meta_action": [
              ""
            ],
            "answer": [
              ""
            ]
          }
        }
      ]
    },
    {
      "step": 3,
      "col": 3089,
      "sampled_token": " the",
      "sampled_prob": 0.99856036901474,
      "entropy": 0.018120821565389633,
      "alternatives": [
        {
          "token": " maintain",
          "token_prob": 0.0001582331897225231,
          "d_curvature_mean": 3.939362068194896e-05,
          "d_curvature_max": 0.00011224625632166862,
          "endpoint_shift_m": 0.07591801881790161,
          "traj_ade_m": 0.022889096289873123,
          "forced_cot": {
            "cot": [
              "Keep distance to maintain scooter ahead since it is directly in our lane"
            ],
            "meta_action": [
              ""
            ],
            "answer": [
              ""
            ]
          }
        },
        {
          "token": " our",
          "token_prob": 0.0001054060339811258,
          "d_curvature_mean": 0.00010228815517621115,
          "d_curvature_max": 0.0002244953066110611,
          "endpoint_shift_m": 0.15378205478191376,
          "traj_ade_m": 0.05432947725057602,
          "forced_cot": {
            "cot": [
              "Keep distance to our scooter ahead since it is directly in our lane"
            ],
            "meta_action": [
              ""
            ],
            "answer": [
              ""
            ]
          }
        },
        {
          "token": " follow",
          "token_prob": 7.711669604759663e-05,
          "d_curvature_mean": 2.7023714210372418e-05,
          "d_curvature_max": 8.035870268940926e-05,
          "endpoint_shift_m": 0.029163360595703125,
          "traj_ade_m": 0.006106522865593433,
          "forced_cot": {
            "cot": [
              "Keep distance to follow scooter ahead since it is directly in our lane"
            ],
            "meta_action": [
              ""
            ],
            "answer": [
              ""
            ]
          }
        },
        {
          "token": " from",
          "token_prob": 6.393199146259576e-05,
          "d_curvature_mean": 2.4027347535593435e-05,
          "d_curvature_max": 6.12274743616581e-05,
          "endpoint_shift_m": 0.07668193429708481,
          "traj_ade_m": 0.023557791486382484,
          "forced_cot": {
            "cot": [
              "Keep distance to from scooter ahead since it is directly in our lane"
            ],
            "meta_action": [
              ""
            ],
            "answer": [
              ""
            ]
          }
        }
      ]
    },
    {
      "step": 4,
      "col": 3090,
      "sampled_token": " scooter",
      "sampled_prob": 0.8895934224128723,
      "entropy": 0.9464749693870544,
      "alternatives": [
        {
          "token": " pedestrian",
          "token_prob": 0.04714672267436981,
          "d_curvature_mean": 3.472221578704193e-05,
          "d_curvature_max": 0.00010459451004862785,
          "endpoint_shift_m": 0.10640222579240799,
          "traj_ade_m": 0.03342365846037865,
          "forced_cot": {
            "cot": [
              "Keep distance to the pedestrian ahead since it is directly in our lane"
            ],
            "meta_action": [
              ""
            ],
            "answer": [
              ""
            ]
          }
        },
        {
          "token": " cyclist",
          "token_prob": 0.013936544768512249,
          "d_curvature_mean": 3.9770286093698815e-05,
          "d_curvature_max": 8.163647726178169e-05,
          "endpoint_shift_m": 0.05320087820291519,
          "traj_ade_m": 0.02090209349989891,
          "forced_cot": {
            "cot": [
              "Keep distance to the cyclist ahead since it is directly in our lane"
            ],
            "meta_action": [
              ""
            ],
            "answer": [
              ""
            ]
          }
        },
        {
          "token": " lead",
          "token_prob": 0.003109663724899292,
          "d_curvature_mean": 5.995484389131889e-05,
          "d_curvature_max": 0.00012245122343301773,
          "endpoint_shift_m": 0.15850165486335754,
          "traj_ade_m": 0.05100233852863312,
          "forced_cot": {
            "cot": [
              "Keep distance to the lead ahead since it is directly in our lane"
            ],
            "meta_action": [
              ""
            ],
            "answer": [
              ""
            ]
          }
        },
        {
          "token": " rider",
          "token_prob": 0.0024986849166452885,
          "d_curvature_mean": 3.635659595602192e-05,
          "d_curvature_max": 9.18388832360506e-05,
          "endpoint_shift_m": 0.29472944140434265,
          "traj_ade_m": 0.10489961504936218,
          "forced_cot": {
            "cot": [
              "Keep distance to the rider ahead since it is directly in our lane"
            ],
            "meta_action": [
              ""
            ],
            "answer": [
              ""
            ]
          }
        }
      ]
    },
    {
      "step": 5,
      "col": 3091,
      "sampled_token": " ahead",
      "sampled_prob": 0.6417021155357361,
      "entropy": 1.2644948959350586,
      "alternatives": [
        {
          "token": " rider",
          "token_prob": 0.26750123500823975,
          "d_curvature_mean": 3.942353941965848e-05,
          "d_curvature_max": 8.163647726178169e-05,
          "endpoint_shift_m": 0.025509079918265343,
          "traj_ade_m": 0.01378579530864954,
          "forced_cot": {
            "cot": [
              "Keep distance to the scooter rider since it is directly in our lane"
            ],
            "meta_action": [
              ""
            ],
            "answer": [
              ""
            ]
          }
        },
        {
          "token": " in",
          "token_prob": 0.042324844747781754,
          "d_curvature_mean": 5.5732092732796445e-05,
          "d_curvature_max": 0.00012245355173945427,
          "endpoint_shift_m": 0.07465286552906036,
          "traj_ade_m": 0.032655347138643265,
          "forced_cot": {
            "cot": [
              "Keep distance to the scooter in since it is directly in our lane"
            ],
            "meta_action": [
              ""
            ],
            "answer": [
              ""
            ]
          }
        },
        {
          "token": " since",
          "token_prob": 0.00782930850982666,
          "d_curvature_mean": 3.73191105609294e-05,
          "d_curvature_max": 0.00011224776972085238,
          "endpoint_shift_m": 0.061631131917238235,
          "traj_ade_m": 0.01346215233206749,
          "forced_cot": {
            "cot": [
              "Keep distance to the scooter since since it is directly in our lane"
            ],
            "meta_action": [
              ""
            ],
            "answer": [
              ""
            ]
          }
        },
        {
          "token": " because",
          "token_prob": 0.004323754925280809,
          "d_curvature_mean": 5.1903836720157415e-05,
          "d_curvature_max": 0.00013265525922179222,
          "endpoint_shift_m": 0.16067105531692505,
          "traj_ade_m": 0.0440625324845314,
          "forced_cot": {
            "cot": [
              "Keep distance to the scooter because since it is directly in our lane"
            ],
            "meta_action": [
              ""
            ],
            "answer": [
              ""
            ]
          }
        }
      ]
    },
    {
      "step": 6,
      "col": 3092,
      "sampled_token": " since",
      "sampled_prob": 0.9866630434989929,
      "entropy": 0.07804940640926361,
      "alternatives": [
        {
          "token": " because",
          "token_prob": 0.011667748913168907,
          "d_curvature_mean": 5.916960162721807e-06,
          "d_curvature_max": 2.0408770069479942e-05,
          "endpoint_shift_m": 0.030007008463144302,
          "traj_ade_m": 0.00946139171719551,
          "forced_cot": {
            "cot": [
              "Keep distance to the scooter ahead because it is directly in our lane"
            ],
            "meta_action": [
              ""
            ],
            "answer": [
              ""
            ]
          }
        },
        {
          "token": " in",
          "token_prob": 0.0010852697305381298,
          "d_curvature_mean": 0.00016199113451875746,
          "d_curvature_max": 0.0003673555329442024,
          "endpoint_shift_m": 0.17178288102149963,
          "traj_ade_m": 0.06459438800811768,
          "forced_cot": {
            "cot": [
              "Keep distance to the scooter ahead in it is directly in our lane"
            ],
            "meta_action": [
              ""
            ],
            "answer": [
              ""
            ]
          }
        },
        {
          "token": " as",
          "token_prob": 0.00025777413975447416,
          "d_curvature_mean": 6.628689880017191e-05,
          "d_curvature_max": 0.00020408909767866135,
          "endpoint_shift_m": 0.02360912598669529,
          "traj_ade_m": 0.010659795254468918,
          "forced_cot": {
            "cot": [
              "Keep distance to the scooter ahead as it is directly in our lane"
            ],
            "meta_action": [
              ""
            ],
            "answer": [
              ""
            ]
          }
        },
        {
          "token": " to",
          "token_prob": 0.00013797657447867095,
          "d_curvature_mean": 0.0001045969474944286,
          "d_curvature_max": 0.0002244953066110611,
          "endpoint_shift_m": 0.04632570222020149,
          "traj_ade_m": 0.01687726005911827,
          "forced_cot": {
            "cot": [
              "Keep distance to the scooter ahead to it is directly in our lane"
            ],
            "meta_action": [
              ""
            ],
            "answer": [
              ""
            ]
          }
        }
      ]
    },
    {
      "step": 7,
      "col": 3093,
      "sampled_token": " it",
      "sampled_prob": 0.9936370849609375,
      "entropy": 0.0453026220202446,
      "alternatives": [
        {
          "token": " they",
          "token_prob": 0.005550411529839039,
          "d_curvature_mean": 3.112770355073735e-05,
          "d_curvature_max": 9.694090113043785e-05,
          "endpoint_shift_m": 0.0305651668459177,
          "traj_ade_m": 0.012405931949615479,
          "forced_cot": {
            "cot": [
              "Keep distance to the scooter ahead since they is directly in our lane"
            ],
            "meta_action": [
              ""
            ],
            "answer": [
              ""
            ]
          }
        },
        {
          "token": " the",
          "token_prob": 0.00020859140204265714,
          "d_curvature_mean": 6.771239713998511e-05,
          "d_curvature_max": 0.00016326876357197762,
          "endpoint_shift_m": 0.06338891386985779,
          "traj_ade_m": 0.023920051753520966,
          "forced_cot": {
            "cot": [
              "Keep distance to the scooter ahead since the is directly in our lane"
            ],
            "meta_action": [
              ""
            ],
            "answer": [
              ""
            ]
          }
        },
        {
          "token": " a",
          "token_prob": 9.256187331629917e-05,
          "d_curvature_mean": 7.694878149777651e-05,
          "d_curvature_max": 0.00016837147995829582,
          "endpoint_shift_m": 0.022815188392996788,
          "traj_ade_m": 0.011308089829981327,
          "forced_cot": {
            "cot": [
              "Keep distance to the scooter ahead since a is directly in our lane"
            ],
            "meta_action": [
              ""
            ],
            "answer": [
              ""
            ]
          }
        },
        {
          "token": " an",
          "token_prob": 2.4146205760189332e-05,
          "d_curvature_mean": 0.00010713452502386644,
          "d_curvature_max": 0.0002449052408337593,
          "endpoint_shift_m": 0.035562481731176376,
          "traj_ade_m": 0.011084062978625298,
          "forced_cot": {
            "cot": [
              "Keep distance to the scooter ahead since an is directly in our lane"
            ],
            "meta_action": [
              ""
            ],
            "answer": [
              ""
            ]
          }
        }
      ]
    },
    {
      "step": 8,
      "col": 3094,
      "sampled_token": " is",
      "sampled_prob": 0.9835087656974792,
      "entropy": 0.10587657988071442,
      "alternatives": [
        {
          "token": " occupies",
          "token_prob": 0.014028999023139477,
          "d_curvature_mean": 2.834492079273332e-05,
          "d_curvature_max": 6.887922063469887e-05,
          "endpoint_shift_m": 0.014075146056711674,
          "traj_ade_m": 0.010195710696280003,
          "forced_cot": {
            "cot": [
              "Keep distance to the scooter ahead since it occupies directly in our lane"
            ],
            "meta_action": [
              ""
            ],
            "answer": [
              ""
            ]
          }
        },
        {
          "token": " moves",
          "token_prob": 0.00021301908418536186,
          "d_curvature_mean": 4.878403706243262e-05,
          "d_curvature_max": 0.00012755626812577248,
          "endpoint_shift_m": 0.04070658981800079,
          "traj_ade_m": 0.010043931193649769,
          "forced_cot": {
            "cot": [
              "Keep distance to the scooter ahead since it moves directly in our lane"
            ],
            "meta_action": [
              ""
            ],
            "answer": [
              ""
            ]
          }
        },
        {
          "token": " occupying",
          "token_prob": 0.00014190129877533764,
          "d_curvature_mean": 4.1688654164317995e-05,
          "d_curvature_max": 8.418597280979156e-05,
          "endpoint_shift_m": 0.03248707205057144,
          "traj_ade_m": 0.010474673472344875,
          "forced_cot": {
            "cot": [
              "Keep distance to the scooter ahead since it occupying directly in our lane"
            ],
            "meta_action": [
              ""
            ],
            "answer": [
              ""
            ]
          }
        },
        {
          "token": " has",
          "token_prob": 8.606749906903133e-05,
          "d_curvature_mean": 2.6028588763438165e-05,
          "d_curvature_max": 6.12274743616581e-05,
          "endpoint_shift_m": 0.049325134605169296,
          "traj_ade_m": 0.011376442387700081,
          "forced_cot": {
            "cot": [
              "Keep distance to the scooter ahead since it has directly in our lane"
            ],
            "meta_action": [
              ""
            ],
            "answer": [
              ""
            ]
          }
        }
      ]
    },
    {
      "step": 9,
      "col": 3095,
      "sampled_token": " directly",
      "sampled_prob": 0.5085107684135437,
      "entropy": 1.4293221235275269,
      "alternatives": [
        {
          "token": " occupying",
          "token_prob": 0.21197882294654846,
          "d_curvature_mean": 9.061668970389292e-05,
          "d_curvature_max": 0.0002142912708222866,
          "endpoint_shift_m": 0.06957193464040756,
          "traj_ade_m": 0.018017126247286797,
          "forced_cot": {
            "cot": [
              "Keep distance to the scooter ahead since it is occupying in our lane"
            ],
            "meta_action": [
              ""
            ],
            "answer": [
              ""
            ]
          }
        },
        {
          "token": " in",
          "token_prob": 0.12857165932655334,
          "d_curvature_mean": 4.139330849284306e-05,
          "d_curvature_max": 0.00012244842946529388,
          "endpoint_shift_m": 0.03525063768029213,
          "traj_ade_m": 0.013502814806997776,
          "forced_cot": {
            "cot": [
              "Keep distance to the scooter ahead since it is in in our lane"
            ],
            "meta_action": [
              ""
            ],
            "answer": [
              ""
            ]
          }
        },
        {
          "token": " moving",
          "token_prob": 0.10658964514732361,
          "d_curvature_mean": 4.5376258640317246e-05,
          "d_curvature_max": 0.00012245448306202888,
          "endpoint_shift_m": 0.062190715223550797,
          "traj_ade_m": 0.02592921257019043,
          "forced_cot": {
            "cot": [
              "Keep distance to the scooter ahead since it is moving in our lane"
            ],
            "meta_action": [
              ""
            ],
            "answer": [
              ""
            ]
          }
        },
        {
          "token": " the",
          "token_prob": 0.015355694107711315,
          "d_curvature_mean": 6.49217254249379e-05,
          "d_curvature_max": 0.00016326550394296646,
          "endpoint_shift_m": 0.14876584708690643,
          "traj_ade_m": 0.05058910325169563,
          "forced_cot": {
            "cot": [
              "Keep distance to the scooter ahead since it is the in our lane"
            ],
            "meta_action": [
              ""
            ],
            "answer": [
              ""
            ]
          }
        }
      ]
    },
    {
      "step": 10,
      "col": 3096,
      "sampled_token": " in",
      "sampled_prob": 0.8987664580345154,
      "entropy": 0.3795918822288513,
      "alternatives": [
        {
          "token": " ahead",
          "token_prob": 0.08898993581533432,
          "d_curvature_mean": 4.001125125796534e-05,
          "d_curvature_max": 0.00011224718764424324,
          "endpoint_shift_m": 0.11017869412899017,
          "traj_ade_m": 0.038915131241083145,
          "forced_cot": {
            "cot": [
              "Keep distance to the scooter ahead since it is directly ahead our lane"
            ],
            "meta_action": [
              ""
            ],
            "answer": [
              ""
            ]
          }
        },
        {
          "token": " blocking",
          "token_prob": 0.009984394535422325,
          "d_curvature_mean": 1.4662433386547491e-05,
          "d_curvature_max": 4.081707447767258e-05,
          "endpoint_shift_m": 0.0506586991250515,
          "traj_ade_m": 0.014850027859210968,
          "forced_cot": {
            "cot": [
              "Keep distance to the scooter ahead since it is directly blocking our lane"
            ],
            "meta_action": [
              ""
            ],
            "answer": [
              ""
            ]
          }
        },
        {
          "token": " occupying",
          "token_prob": 0.0007699137204326689,
          "d_curvature_mean": 3.071632454521023e-05,
          "d_curvature_max": 6.122840568423271e-05,
          "endpoint_shift_m": 0.014519788324832916,
          "traj_ade_m": 0.004530191887170076,
          "forced_cot": {
            "cot": [
              "Keep distance to the scooter ahead since it is directly occupying our lane"
            ],
            "meta_action": [
              ""
            ],
            "answer": [
              ""
            ]
          }
        },
        {
          "token": " obstruct",
          "token_prob": 0.00019466466619633138,
          "d_curvature_mean": 2.4719982320675626e-05,
          "d_curvature_max": 4.5919790863990784e-05,
          "endpoint_shift_m": 0.034315790981054306,
          "traj_ade_m": 0.01314481906592846,
          "forced_cot": {
            "cot": [
              "Keep distance to the scooter ahead since it is directly obstruct our lane"
            ],
            "meta_action": [
              ""
            ],
            "answer": [
              ""
            ]
          }
        }
      ]
    },
    {
      "step": 11,
      "col": 3097,
      "sampled_token": " our",
      "sampled_prob": 0.9916208982467651,
      "entropy": 0.04998132213950157,
      "alternatives": [
        {
          "token": " front",
          "token_prob": 0.00805941503494978,
          "d_curvature_mean": 2.5908873794833198e-05,
          "d_curvature_max": 6.122468039393425e-05,
          "endpoint_shift_m": 0.02106247842311859,
          "traj_ade_m": 0.012329718098044395,
          "forced_cot": {
            "cot": [
              "Keep distance to the scooter ahead since it is directly in front lane"
            ],
            "meta_action": [
              ""
            ],
            "answer": [
              ""
            ]
          }
        },
        {
          "token": " the",
          "token_prob": 0.00029356416780501604,
          "d_curvature_mean": 4.874379010288976e-05,
          "d_curvature_max": 0.00012245262041687965,
          "endpoint_shift_m": 0.0045532118529081345,
          "traj_ade_m": 0.003064894350245595,
          "forced_cot": {
            "cot": [
              "Keep distance to the scooter ahead since it is directly in the lane"
            ],
            "meta_action": [
              ""
            ],
            "answer": [
              ""
            ]
          }
        },
        {
          "token": " your",
          "token_prob": 4.7450225792999845e-06,
          "d_curvature_mean": 3.3773128961911425e-05,
          "d_curvature_max": 8.163182064890862e-05,
          "endpoint_shift_m": 0.06913924217224121,
          "traj_ade_m": 0.024988217279314995,
          "forced_cot": {
            "cot": [
              "Keep distance to the scooter ahead since it is directly in your lane"
            ],
            "meta_action": [
              ""
            ],
            "answer": [
              ""
            ]
          }
        },
        {
          "token": " my",
          "token_prob": 4.320391781220678e-06,
          "d_curvature_mean": 4.0751729102339596e-05,
          "d_curvature_max": 0.00010204501450061798,
          "endpoint_shift_m": 0.01884445734322071,
          "traj_ade_m": 0.008219148963689804,
          "forced_cot": {
            "cot": [
              "Keep distance to the scooter ahead since it is directly in my lane"
            ],
            "meta_action": [
              ""
            ],
            "answer": [
              ""
            ]
          }
        }
      ]
    },
    {
      "step": 12,
      "col": 3098,
      "sampled_token": " lane",
      "sampled_prob": 0.9849328398704529,
      "entropy": 0.08921771496534348,
      "alternatives": [
        {
          "token": " path",
          "token_prob": 0.012398474849760532,
          "d_curvature_mean": 2.096096613968257e-05,
          "d_curvature_max": 6.122654303908348e-05,
          "endpoint_shift_m": 0.01892932876944542,
          "traj_ade_m": 0.0044918968342244625,
          "forced_cot": {
            "cot": [
              "Keep distance to the scooter ahead since it is directly in our path"
            ],
            "meta_action": [
              ""
            ],
            "answer": [
              ""
            ]
          }
        },
        {
          "token": " travel",
          "token_prob": 0.0021545318886637688,
          "d_curvature_mean": 1.4208550965122413e-05,
          "d_curvature_max": 5.612371023744345e-05,
          "endpoint_shift_m": 0.08573165535926819,
          "traj_ade_m": 0.028546052053570747,
          "forced_cot": {
            "cot": [
              "Keep distance to the scooter ahead since it is directly in our travel"
            ],
            "meta_action": [
              ""
            ],
            "answer": [
              ""
            ]
          }
        },
        {
          "token": " same",
          "token_prob": 7.14557827450335e-05,
          "d_curvature_mean": 2.0431180018931627e-05,
          "d_curvature_max": 8.673639968037605e-05,
          "endpoint_shift_m": 0.038524121046066284,
          "traj_ade_m": 0.013130107894539833,
          "forced_cot": {
            "cot": [
              "Keep distance to the scooter ahead since it is directly in our same"
            ],
            "meta_action": [
              ""
            ],
            "answer": [
              ""
            ]
          }
        },
        {
          "token": " ego",
          "token_prob": 5.227816291153431e-05,
          "d_curvature_mean": 2.3195250832941383e-05,
          "d_curvature_max": 0.00010714621748775244,
          "endpoint_shift_m": 0.0970621183514595,
          "traj_ade_m": 0.03689903765916824,
          "forced_cot": {
            "cot": [
              "Keep distance to the scooter ahead since it is directly in our ego"
            ],
            "meta_action": [
              ""
            ],
            "answer": [
              ""
            ]
          }
        }
      ]
    }
  ],
  "counterfactual_sweep": [
    {
      "step": 0,
      "col": 3086,
      "sampled_token": "Keep",
      "sampled_prob": 0.5580194592475891,
      "entropy": 1.261070966720581,
      "alternatives": [
        {
          "token": "N",
          "token_prob": 0.2805897891521454,
          "d_curvature_mean": 0.00026819281629286706,
          "d_curvature_max": 0.0005714432336390018,
          "endpoint_shift_m": 0.6970072388648987,
          "traj_ade_m": 0.20240569114685059,
          "forced_cot": {
            "cot": [
              "Nudge to the left to increase clearance from the scooter rider ahead"
            ],
            "meta_action": [
              ""
            ],
            "answer": [
              ""
            ]
          }
        },
        {
          "token": "Y",
          "token_prob": 0.10649987310171127,
          "d_curvature_mean": 4.933493255521171e-05,
          "d_curvature_max": 0.0001020459458231926,
          "endpoint_shift_m": 0.243571475148201,
          "traj_ade_m": 0.08238615095615387,
          "forced_cot": {
            "cot": [
              "Yield to the scooter rider since they are directly ahead in our lane"
            ],
            "meta_action": [
              ""
            ],
            "answer": [
              ""
            ]
          }
        },
        {
          "token": "Acceler",
          "token_prob": 0.015342761762440205,
          "d_curvature_mean": 0.0051351008005440235,
          "d_curvature_max": 0.009061431512236595,
          "endpoint_shift_m": 4.8932719230651855,
          "traj_ade_m": 1.5315024852752686,
          "forced_cot": {
            "cot": [
              "Accelerate gently because the scooter rider has cleared our lane and parked cars remain outside our travel path, so proceeding straight is safe with cautious distance to the scooter ahead in our lane."
            ],
            "meta_action": [
              ""
            ],
            "answer": [
              ""
            ]
          }
        },
        {
          "token": "Slow",
          "token_prob": 0.00821238849312067,
          "d_curvature_mean": 8.195460395654663e-05,
          "d_curvature_max": 0.00017092283815145493,
          "endpoint_shift_m": 0.09806420654058456,
          "traj_ade_m": 0.032123107463121414,
          "forced_cot": {
            "cot": [
              "Slow down to keep distance from the scooter ahead since it is occupying our lane"
            ],
            "meta_action": [
              ""
            ],
            "answer": [
              ""
            ]
          }
        }
      ]
    },
    {
      "step": 1,
      "col": 3087,
      "sampled_token": " distance",
      "sampled_prob": 0.9987725615501404,
      "entropy": 0.010173918679356575,
      "alternatives": [
        {
          "token": " lane",
          "token_prob": 0.0010985895060002804,
          "d_curvature_mean": 0.0003695999621413648,
          "d_curvature_max": 0.0007143043912947178,
          "endpoint_shift_m": 1.017338752746582,
          "traj_ade_m": 0.3244319260120392,
          "forced_cot": {
            "cot": [
              "Keep lane since the lane is clear and no immediate hazard is present"
            ],
            "meta_action": [
              ""
            ],
            "answer": [
              ""
            ]
          }
        },
        {
          "token": " at",
          "token_prob": 4.6783585275989026e-05,
          "d_curvature_mean": 0.00015513428661506623,
          "d_curvature_max": 0.000346943736076355,
          "endpoint_shift_m": 0.4839087128639221,
          "traj_ade_m": 0.12665174901485443,
          "forced_cot": {
            "cot": [
              "Keep at the center of our lane to continue driving since no immediate hazard is in our lane"
            ],
            "meta_action": [
              ""
            ],
            "answer": [
              ""
            ]
          }
        },
        {
          "token": " left",
          "token_prob": 3.878495408571325e-05,
          "d_curvature_mean": 0.000158415554324165,
          "d_curvature_max": 0.0002653123810887337,
          "endpoint_shift_m": 0.29342517256736755,
          "traj_ade_m": 0.0732077956199646,
          "forced_cot": {
            "cot": [
              "Keep left within lane due to a scooter rider ahead in our lane"
            ],
            "meta_action": [
              ""
            ],
            "answer": [
              ""
            ]
          }
        },
        {
          "token": " speed",
          "token_prob": 1.1112075299024582e-05,
          "d_curvature_mean": 0.00043373083462938666,
          "d_curvature_max": 0.0008367565460503101,
          "endpoint_shift_m": 1.1605244874954224,
          "traj_ade_m": 0.4074708819389343,
          "forced_cot": {
            "cot": [
              "Keep speed and maintain a safe following distance because the scooter rider ahead is moving slowly in our lane and we are not yet close enough for a safe pass, so we must continue behind at a safe gap until it clears."
            ],
            "meta_action": [
              ""
            ],
            "answer": [
              ""
            ]
          }
        }
      ]
    },
    {
      "step": 2,
      "col": 3088,
      "sampled_token": " to",
      "sampled_prob": 0.902679443359375,
      "entropy": 0.3603723645210266,
      "alternatives": [
        {
          "token": " from",
          "token_prob": 0.08937736600637436,
          "d_curvature_mean": 3.06875845126342e-05,
          "d_curvature_max": 7.525680121034384e-05,
          "endpoint_shift_m": 0.10060511529445648,
          "traj_ade_m": 0.029602523893117905,
          "forced_cot": {
            "cot": [
              "Keep distance from the scooter ahead since it is directly in our lane"
            ],
            "meta_action": [
              ""
            ],
            "answer": [
              ""
            ]
          }
        },
        {
          "token": " since",
          "token_prob": 0.0036890446208417416,
          "d_curvature_mean": 0.00012374915240798146,
          "d_curvature_max": 0.00027041370049118996,
          "endpoint_shift_m": 0.1752370148897171,
          "traj_ade_m": 0.07200170308351517,
          "forced_cot": {
            "cot": [
              "Keep distance since a scooter is directly ahead in our lane"
            ],
            "meta_action": [
              ""
            ],
            "answer": [
              ""
            ]
          }
        },
        {
          "token": " because",
          "token_prob": 0.0028730309568345547,
          "d_curvature_mean": 0.00011752600403269753,
          "d_curvature_max": 0.000214290339499712,
          "endpoint_shift_m": 0.16968536376953125,
          "traj_ade_m": 0.0816367045044899,
          "forced_cot": {
            "cot": [
              "Keep distance because a scooter is directly ahead in our lane"
            ],
            "meta_action": [
              ""
            ],
            "answer": [
              ""
            ]
          }
        },
        {
          "token": " due",
          "token_prob": 0.0003028151986654848,
          "d_curvature_mean": 7.198537059593946e-05,
          "d_curvature_max": 0.00016327062621712685,
          "endpoint_shift_m": 0.2514508366584778,
          "traj_ade_m": 0.11286850273609161,
          "forced_cot": {
            "cot": [
              "Keep distance due to a scooter rider ahead in our lane"
            ],
            "meta_action": [
              ""
            ],
            "answer": [
              ""
            ]
          }
        }
      ]
    },
    {
      "step": 3,
      "col": 3089,
      "sampled_token": " the",
      "sampled_prob": 0.99856036901474,
      "entropy": 0.018120821565389633,
      "alternatives": [
        {
          "token": " maintain",
          "token_prob": 0.0001582331897225231,
          "d_curvature_mean": 2.8858334189862944e-05,
          "d_curvature_max": 9.693950414657593e-05,
          "endpoint_shift_m": 0.24103835225105286,
          "traj_ade_m": 0.09166485071182251,
          "forced_cot": {
            "cot": [
              "Keep distance to maintain a safe gap to the scooter ahead since it is directly in our lane"
            ],
            "meta_action": [
              ""
            ],
            "answer": [
              ""
            ]
          }
        },
        {
          "token": " our",
          "token_prob": 0.0001054060339811258,
          "d_curvature_mean": 9.717344073578715e-05,
          "d_curvature_max": 0.000214290339499712,
          "endpoint_shift_m": 0.16413940489292145,
          "traj_ade_m": 0.05836969241499901,
          "forced_cot": {
            "cot": [
              "Keep distance to our scooter ahead since it is directly in our lane"
            ],
            "meta_action": [
              ""
            ],
            "answer": [
              ""
            ]
          }
        },
        {
          "token": " follow",
          "token_prob": 7.711669604759663e-05,
          "d_curvature_mean": 2.8051381377736107e-05,
          "d_curvature_max": 6.122654303908348e-05,
          "endpoint_shift_m": 0.1446724385023117,
          "traj_ade_m": 0.04165863245725632,
          "forced_cot": {
            "cot": [
              "Keep distance to follow the scooter rider since it is directly ahead in our lane"
            ],
            "meta_action": [
              ""
            ],
            "answer": [
              ""
            ]
          }
        },
        {
          "token": " from",
          "token_prob": 6.393199146259576e-05,
          "d_curvature_mean": 2.432124711049255e-05,
          "d_curvature_max": 6.122840568423271e-05,
          "endpoint_shift_m": 0.07677474617958069,
          "traj_ade_m": 0.02352796122431755,
          "forced_cot": {
            "cot": [
              "Keep distance to from the scooter rider since it is directly ahead in our lane"
            ],
            "meta_action": [
              ""
            ],
            "answer": [
              ""
            ]
          }
        }
      ]
    },
    {
      "step": 4,
      "col": 3090,
      "sampled_token": " scooter",
      "sampled_prob": 0.8895934224128723,
      "entropy": 0.9464749693870544,
      "alternatives": [
        {
          "token": " pedestrian",
          "token_prob": 0.04714672267436981,
          "d_curvature_mean": 4.9452544772066176e-05,
          "d_curvature_max": 0.00012245308607816696,
          "endpoint_shift_m": 0.08330041915178299,
          "traj_ade_m": 0.02180136740207672,
          "forced_cot": {
            "cot": [
              "Keep distance to the pedestrian ahead since they are walking in our lane"
            ],
            "meta_action": [
              ""
            ],
            "answer": [
              ""
            ]
          }
        },
        {
          "token": " cyclist",
          "token_prob": 0.013936544768512249,
          "d_curvature_mean": 2.9342485504457727e-05,
          "d_curvature_max": 6.122654303908348e-05,
          "endpoint_shift_m": 0.009595435112714767,
          "traj_ade_m": 0.004622650798410177,
          "forced_cot": {
            "cot": [
              "Keep distance to the cyclist since it is directly ahead in our lane"
            ],
            "meta_action": [
              ""
            ],
            "answer": [
              ""
            ]
          }
        },
        {
          "token": " lead",
          "token_prob": 0.003109663724899292,
          "d_curvature_mean": 1.955782136064954e-05,
          "d_curvature_max": 7.142988033592701e-05,
          "endpoint_shift_m": 0.050453078001737595,
          "traj_ade_m": 0.01501297764480114,
          "forced_cot": {
            "cot": [
              "Keep distance to the lead scooter since it is directly ahead in our lane"
            ],
            "meta_action": [
              ""
            ],
            "answer": [
              ""
            ]
          }
        },
        {
          "token": " rider",
          "token_prob": 0.0024986849166452885,
          "d_curvature_mean": 3.6556572013068944e-05,
          "d_curvature_max": 9.184051305055618e-05,
          "endpoint_shift_m": 0.29457229375839233,
          "traj_ade_m": 0.10483340919017792,
          "forced_cot": {
            "cot": [
              "Keep distance to the rider ahead since it is directly in our lane"
            ],
            "meta_action": [
              ""
            ],
            "answer": [
              ""
            ]
          }
        }
      ]
    },
    {
      "step": 5,
      "col": 3091,
      "sampled_token": " ahead",
      "sampled_prob": 0.6417021155357361,
      "entropy": 1.2644948959350586,
      "alternatives": [
        {
          "token": " rider",
          "token_prob": 0.26750123500823975,
          "d_curvature_mean": 1.392399917676812e-05,
          "d_curvature_max": 4.081818042322993e-05,
          "endpoint_shift_m": 0.04826167970895767,
          "traj_ade_m": 0.016046058386564255,
          "forced_cot": {
            "cot": [
              "Keep distance to the scooter rider since it is directly ahead in our lane"
            ],
            "meta_action": [
              ""
            ],
            "answer": [
              ""
            ]
          }
        },
        {
          "token": " in",
          "token_prob": 0.042324844747781754,
          "d_curvature_mean": 7.952331361593679e-05,
          "d_curvature_max": 0.00016327062621712685,
          "endpoint_shift_m": 0.02022707276046276,
          "traj_ade_m": 0.006588703487068415,
          "forced_cot": {
            "cot": [
              "Keep distance to the scooter in our lane since it is directly ahead"
            ],
            "meta_action": [
              ""
            ],
            "answer": [
              ""
            ]
          }
        },
        {
          "token": " since",
          "token_prob": 0.00782930850982666,
          "d_curvature_mean": 2.0325893274275586e-05,
          "d_curvature_max": 6.632902659475803e-05,
          "endpoint_shift_m": 0.06259805709123611,
          "traj_ade_m": 0.023320823907852173,
          "forced_cot": {
            "cot": [
              "Keep distance to the scooter since it is directly ahead in our lane"
            ],
            "meta_action": [
              ""
            ],
            "answer": [
              ""
            ]
          }
        },
        {
          "token": " because",
          "token_prob": 0.004323754925280809,
          "d_curvature_mean": 2.3275561034097336e-05,
          "d_curvature_max": 8.163414895534515e-05,
          "endpoint_shift_m": 0.008474585600197315,
          "traj_ade_m": 0.0067352126352488995,
          "forced_cot": {
            "cot": [
              "Keep distance to the scooter because it is directly ahead in our lane"
            ],
            "meta_action": [
              ""
            ],
            "answer": [
              ""
            ]
          }
        }
      ]
    },
    {
      "step": 6,
      "col": 3092,
      "sampled_token": " since",
      "sampled_prob": 0.9866630434989929,
      "entropy": 0.07804940640926361,
      "alternatives": [
        {
          "token": " because",
          "token_prob": 0.011667748913168907,
          "d_curvature_mean": 6.382821993611287e-06,
          "d_curvature_max": 2.0409876015037298e-05,
          "endpoint_shift_m": 0.024665387347340584,
          "traj_ade_m": 0.006857840344309807,
          "forced_cot": {
            "cot": [
              "Keep distance to the scooter ahead because it is directly in our lane"
            ],
            "meta_action": [
              ""
            ],
            "answer": [
              ""
            ]
          }
        },
        {
          "token": " in",
          "token_prob": 0.0010852697305381298,
          "d_curvature_mean": 6.023830792400986e-05,
          "d_curvature_max": 0.0001734723336994648,
          "endpoint_shift_m": 0.04473021999001503,
          "traj_ade_m": 0.013953867368400097,
          "forced_cot": {
            "cot": [
              "Keep distance to the scooter ahead in our lane since it is directly in our path"
            ],
            "meta_action": [
              ""
            ],
            "answer": [
              ""
            ]
          }
        },
        {
          "token": " as",
          "token_prob": 0.00025777413975447416,
          "d_curvature_mean": 6.369836046360433e-05,
          "d_curvature_max": 0.00018368056043982506,
          "endpoint_shift_m": 0.01813831552863121,
          "traj_ade_m": 0.007384526543319225,
          "forced_cot": {
            "cot": [
              "Keep distance to the scooter ahead as it is directly in our lane"
            ],
            "meta_action": [
              ""
            ],
            "answer": [
              ""
            ]
          }
        },
        {
          "token": " to",
          "token_prob": 0.00013797657447867095,
          "d_curvature_mean": 3.868387284455821e-05,
          "d_curvature_max": 8.418632205575705e-05,
          "endpoint_shift_m": 0.015357913449406624,
          "traj_ade_m": 0.008227843791246414,
          "forced_cot": {
            "cot": [
              "Keep distance to the scooter ahead to maintain a safe following gap"
            ],
            "meta_action": [
              ""
            ],
            "answer": [
              ""
            ]
          }
        }
      ]
    },
    {
      "step": 7,
      "col": 3093,
      "sampled_token": " it",
      "sampled_prob": 0.9936370849609375,
      "entropy": 0.0453026220202446,
      "alternatives": [
        {
          "token": " they",
          "token_prob": 0.005550411529839039,
          "d_curvature_mean": 3.3945379982469603e-05,
          "d_curvature_max": 9.694090113043785e-05,
          "endpoint_shift_m": 0.01574288308620453,
          "traj_ade_m": 0.006660562939941883,
          "forced_cot": {
            "cot": [
              "Keep distance to the scooter ahead since they are directly in our lane"
            ],
            "meta_action": [
              ""
            ],
            "answer": [
              ""
            ]
          }
        },
        {
          "token": " the",
          "token_prob": 0.00020859140204265714,
          "d_curvature_mean": 1.7686374121694826e-05,
          "d_curvature_max": 4.0819752030074596e-05,
          "endpoint_shift_m": 0.07316283881664276,
          "traj_ade_m": 0.02412276901304722,
          "forced_cot": {
            "cot": [
              "Keep distance to the scooter ahead since the rider is directly in our lane"
            ],
            "meta_action": [
              ""
            ],
            "answer": [
              ""
            ]
          }
        },
        {
          "token": " a",
          "token_prob": 9.256187331629917e-05,
          "d_curvature_mean": 3.724245834746398e-05,
          "d_curvature_max": 8.163275197148323e-05,
          "endpoint_shift_m": 0.030140036717057228,
          "traj_ade_m": 0.009499263018369675,
          "forced_cot": {
            "cot": [
              "Keep distance to the scooter ahead since a slow rider is occupying our lane"
            ],
            "meta_action": [
              ""
            ],
            "answer": [
              ""
            ]
          }
        },
        {
          "token": " an",
          "token_prob": 2.4146205760189332e-05,
          "d_curvature_mean": 0.00010588971781544387,
          "d_curvature_max": 0.00020408444106578827,
          "endpoint_shift_m": 0.437883585691452,
          "traj_ade_m": 0.1312291920185089,
          "forced_cot": {
            "cot": [
              "Keep distance to the scooter ahead since an immediate pass is unsafe"
            ],
            "meta_action": [
              ""
            ],
            "answer": [
              ""
            ]
          }
        }
      ]
    },
    {
      "step": 8,
      "col": 3094,
      "sampled_token": " is",
      "sampled_prob": 0.9835087656974792,
      "entropy": 0.10587657988071442,
      "alternatives": [
        {
          "token": " occupies",
          "token_prob": 0.014028999023139477,
          "d_curvature_mean": 4.81639763165731e-05,
          "d_curvature_max": 0.00010204128921031952,
          "endpoint_shift_m": 0.01507627684623003,
          "traj_ade_m": 0.00576747627928853,
          "forced_cot": {
            "cot": [
              "Keep distance to the scooter ahead since it occupies our lane"
            ],
            "meta_action": [
              ""
            ],
            "answer": [
              ""
            ]
          }
        },
        {
          "token": " moves",
          "token_prob": 0.00021301908418536186,
          "d_curvature_mean": 1.920410977618303e-05,
          "d_curvature_max": 7.143011316657066e-05,
          "endpoint_shift_m": 0.0946454405784607,
          "traj_ade_m": 0.0255451463162899,
          "forced_cot": {
            "cot": [
              "Keep distance to the scooter ahead since it moves slowly in our lane"
            ],
            "meta_action": [
              ""
            ],
            "answer": [
              ""
            ]
          }
        },
        {
          "token": " occupying",
          "token_prob": 0.00014190129877533764,
          "d_curvature_mean": 4.822998016607016e-05,
          "d_curvature_max": 0.0001428588293492794,
          "endpoint_shift_m": 0.16966582834720612,
          "traj_ade_m": 0.05348476022481918,
          "forced_cot": {
            "cot": [
              "Keep distance to the scooter ahead since it occupying our lane is slow"
            ],
            "meta_action": [
              ""
            ],
            "answer": [
              ""
            ]
          }
        },
        {
          "token": " has",
          "token_prob": 8.606749906903133e-05,
          "d_curvature_mean": 7.315426773857325e-05,
          "d_curvature_max": 0.00018367497250437737,
          "endpoint_shift_m": 0.11739376187324524,
          "traj_ade_m": 0.035282548516988754,
          "forced_cot": {
            "cot": [
              "Keep distance to the scooter ahead since it has merged into our lane"
            ],
            "meta_action": [
              ""
            ],
            "answer": [
              ""
            ]
          }
        }
      ]
    },
    {
      "step": 9,
      "col": 3095,
      "sampled_token": " directly",
      "sampled_prob": 0.5085107684135437,
      "entropy": 1.4293221235275269,
      "alternatives": [
        {
          "token": " occupying",
          "token_prob": 0.21197882294654846,
          "d_curvature_mean": 7.603284757351503e-05,
          "d_curvature_max": 0.0001938813365995884,
          "endpoint_shift_m": 0.07447304576635361,
          "traj_ade_m": 0.02113216370344162,
          "forced_cot": {
            "cot": [
              "Keep distance to the scooter ahead since it is occupying our lane"
            ],
            "meta_action": [
              ""
            ],
            "answer": [
              ""
            ]
          }
        },
        {
          "token": " in",
          "token_prob": 0.12857165932655334,
          "d_curvature_mean": 4.385663487482816e-05,
          "d_curvature_max": 0.00012244842946529388,
          "endpoint_shift_m": 0.06495874375104904,
          "traj_ade_m": 0.022082852199673653,
          "forced_cot": {
            "cot": [
              "Keep distance to the scooter ahead since it is in our lane"
            ],
            "meta_action": [
              ""
            ],
            "answer": [
              ""
            ]
          }
        },
        {
          "token": " moving",
          "token_prob": 0.10658964514732361,
          "d_curvature_mean": 5.19819077453576e-05,
          "d_curvature_max": 0.00012245122343301773,
          "endpoint_shift_m": 0.07143346220254898,
          "traj_ade_m": 0.016437016427516937,
          "forced_cot": {
            "cot": [
              "Keep distance to the scooter ahead since it is moving slowly in our lane"
            ],
            "meta_action": [
              ""
            ],
            "answer": [
              ""
            ]
          }
        },
        {
          "token": " the",
          "token_prob": 0.015355694107711315,
          "d_curvature_mean": 0.00011591204383876175,
          "d_curvature_max": 0.00029592402279376984,
          "endpoint_shift_m": 0.03170996531844139,
          "traj_ade_m": 0.020754972472786903,
          "forced_cot": {
            "cot": [
              "Keep distance to the scooter ahead since it is the lead obstacle in our lane"
            ],
            "meta_action": [
              ""
            ],
            "answer": [
              ""
            ]
          }
        }
      ]
    },
    {
      "step": 10,
      "col": 3096,
      "sampled_token": " in",
      "sampled_prob": 0.8987664580345154,
      "entropy": 0.3795918822288513,
      "alternatives": [
        {
          "token": " ahead",
          "token_prob": 0.08898993581533432,
          "d_curvature_mean": 2.948248220491223e-05,
          "d_curvature_max": 6.122677586972713e-05,
          "endpoint_shift_m": 0.020406153053045273,
          "traj_ade_m": 0.011589374393224716,
          "forced_cot": {
            "cot": [
              "Keep distance to the scooter ahead since it is directly ahead in our lane"
            ],
            "meta_action": [
              ""
            ],
            "answer": [
              ""
            ]
          }
        },
        {
          "token": " blocking",
          "token_prob": 0.009984394535422325,
          "d_curvature_mean": 1.6434951248811558e-05,
          "d_curvature_max": 4.081893712282181e-05,
          "endpoint_shift_m": 0.050317488610744476,
          "traj_ade_m": 0.016474654898047447,
          "forced_cot": {
            "cot": [
              "Keep distance to the scooter ahead since it is directly blocking our lane"
            ],
            "meta_action": [
              ""
            ],
            "answer": [
              ""
            ]
          }
        },
        {
          "token": " occupying",
          "token_prob": 0.0007699137204326689,
          "d_curvature_mean": 3.0458531909971498e-05,
          "d_curvature_max": 6.122700870037079e-05,
          "endpoint_shift_m": 0.018543342128396034,
          "traj_ade_m": 0.0042889839969575405,
          "forced_cot": {
            "cot": [
              "Keep distance to the scooter ahead since it is directly occupying our lane"
            ],
            "meta_action": [
              ""
            ],
            "answer": [
              ""
            ]
          }
        },
        {
          "token": " obstruct",
          "token_prob": 0.00019466466619633138,
          "d_curvature_mean": 2.2170663214637898e-05,
          "d_curvature_max": 5.102180875837803e-05,
          "endpoint_shift_m": 0.1348053514957428,
          "traj_ade_m": 0.043256718665361404,
          "forced_cot": {
            "cot": [
              "Keep distance to the scooter ahead since it is directly obstructing our lane"
            ],
            "meta_action": [
              ""
            ],
            "answer": [
              ""
            ]
          }
        }
      ]
    },
    {
      "step": 11,
      "col": 3097,
      "sampled_token": " our",
      "sampled_prob": 0.9916208982467651,
      "entropy": 0.04998132213950157,
      "alternatives": [
        {
          "token": " front",
          "token_prob": 0.00805941503494978,
          "d_curvature_mean": 2.5922456188709475e-05,
          "d_curvature_max": 6.122561171650887e-05,
          "endpoint_shift_m": 0.06692471355199814,
          "traj_ade_m": 0.016877833753824234,
          "forced_cot": {
            "cot": [
              "Keep distance to the scooter ahead since it is directly in front in our lane"
            ],
            "meta_action": [
              ""
            ],
            "answer": [
              ""
            ]
          }
        },
        {
          "token": " the",
          "token_prob": 0.00029356416780501604,
          "d_curvature_mean": 4.3519612518139184e-05,
          "d_curvature_max": 0.00010204361751675606,
          "endpoint_shift_m": 0.010581925511360168,
          "traj_ade_m": 0.003028185572475195,
          "forced_cot": {
            "cot": [
              "Keep distance to the scooter ahead since it is directly in the lane"
            ],
            "meta_action": [
              ""
            ],
            "answer": [
              ""
            ]
          }
        },
        {
          "token": " your",
          "token_prob": 4.7450225792999845e-06,
          "d_curvature_mean": 2.957793913083151e-05,
          "d_curvature_max": 6.122700870037079e-05,
          "endpoint_shift_m": 0.06634429097175598,
          "traj_ade_m": 0.024155432358384132,
          "forced_cot": {
            "cot": [
              "Keep distance to the scooter ahead since it is directly in your lane"
            ],
            "meta_action": [
              ""
            ],
            "answer": [
              ""
            ]
          }
        },
        {
          "token": " my",
          "token_prob": 4.320391781220678e-06,
          "d_curvature_mean": 4.415162402438e-05,
          "d_curvature_max": 0.00010204501450061798,
          "endpoint_shift_m": 0.019248921424150467,
          "traj_ade_m": 0.009575434029102325,
          "forced_cot": {
            "cot": [
              "Keep distance to the scooter ahead since it is directly in my lane"
            ],
            "meta_action": [
              ""
            ],
            "answer": [
              ""
            ]
          }
        }
      ]
    },
    {
      "step": 12,
      "col": 3098,
      "sampled_token": " lane",
      "sampled_prob": 0.9849328398704529,
      "entropy": 0.08921771496534348,
      "alternatives": [
        {
          "token": " path",
          "token_prob": 0.012398474849760532,
          "d_curvature_mean": 1.8573073248262517e-05,
          "d_curvature_max": 5.10229729115963e-05,
          "endpoint_shift_m": 0.01576916314661503,
          "traj_ade_m": 0.00367545778863132,
          "forced_cot": {
            "cot": [
              "Keep distance to the scooter ahead since it is directly in our path"
            ],
            "meta_action": [
              ""
            ],
            "answer": [
              ""
            ]
          }
        },
        {
          "token": " travel",
          "token_prob": 0.0021545318886637688,
          "d_curvature_mean": 1.2198051990708336e-05,
          "d_curvature_max": 4.08184714615345e-05,
          "endpoint_shift_m": 0.016463084146380424,
          "traj_ade_m": 0.00491658691316843,
          "forced_cot": {
            "cot": [
              "Keep distance to the scooter ahead since it is directly in our travel lane"
            ],
            "meta_action": [
              ""
            ],
            "answer": [
              ""
            ]
          }
        },
        {
          "token": " same",
          "token_prob": 7.14557827450335e-05,
          "d_curvature_mean": 8.96683195605874e-06,
          "d_curvature_max": 3.0613504350185394e-05,
          "endpoint_shift_m": 0.006849273573607206,
          "traj_ade_m": 0.004851650446653366,
          "forced_cot": {
            "cot": [
              "Keep distance to the scooter ahead since it is directly in our same lane"
            ],
            "meta_action": [
              ""
            ],
            "answer": [
              ""
            ]
          }
        },
        {
          "token": " ego",
          "token_prob": 5.227816291153431e-05,
          "d_curvature_mean": 1.0915056918747723e-05,
          "d_curvature_max": 2.5510787963867188e-05,
          "endpoint_shift_m": 0.029050365090370178,
          "traj_ade_m": 0.00849856436252594,
          "forced_cot": {
            "cot": [
              "Keep distance to the scooter ahead since it is directly in our ego lane"
            ],
            "meta_action": [
              ""
            ],
            "answer": [
              ""
            ]
          }
        }
      ]
    }
  ]
}